setup.cfg
setup.py
bin/enru
enru/__init__.py
enru/enru.py
enru/exceptions.py
enru.egg-info/PKG-INFO
enru.egg-info/SOURCES.txt
enru.egg-info/dependency_links.txt
enru.egg-info/requires.txt
enru.egg-info/top_level.txt
enru/adapters/__init__.py
enru/adapters/base.py
enru/adapters/yandex.py
enru/tests/__init__.py
enru/tests/test_yandex.py