Metadata-Version: 1.0
Name: enru
Version: 1.1
Summary: Simple dictionaries translation parser
Home-page: https://github.com/everyonesdesign/enru/
Author: Yura Trambitskiy
Author-email: tr.yura@yahoo.com
License: MIT
Platform: UNKNOWN
